textunits/__init__.py
textunits/tags_features.py
textunits/textunits.py
textunits/utils.py
textunits-0.0.3.dist-info/LICENSE
textunits-0.0.3.dist-info/METADATA
textunits-0.0.3.dist-info/WHEEL
textunits-0.0.3.dist-info/top_level.txt
textunits-0.0.3.dist-info/RECORD
